glview/__init__.py
glview/ae.py
glview/argv.py
glview/glrenderer.py
glview/glview.py
glview/imageprovider.py
glview/panzoom.vs
glview/postprocess.fs
glview/pygletui.py
glview/texture.fs
glview/texture.py
glview/version.py
glview-1.19.0.dist-info/LICENSE
glview-1.19.0.dist-info/METADATA
glview-1.19.0.dist-info/WHEEL
glview-1.19.0.dist-info/entry_points.txt
glview-1.19.0.dist-info/top_level.txt
glview-1.19.0.dist-info/zip-safe
glview-1.19.0.dist-info/RECORD
